accum_avg/div.v
module div(
	input wire clk,
	input wire start,
	input wire [31:0] dividend,
	input wire [31:0] divider,
	output wire [31:0] quotient
);

assign quotient = result;

reg [31:0] quotient_reg;
reg [31:0] result;
reg [63:0] dividend_copy, divider_copy, diff;
wire [31:0] remander = dividend_copy[31:0];

reg [5:0] bit = 6'd0;
wire ready = !bit;

always @( posedge clk )
begin
	if ( ready && start ) begin
		bit = 6'd32;
		result <= quotient_reg;
		quotient_reg = 0;
		dividend_copy = {32'd0, dividend};	
		divider_copy = {1'b0, divider, 31'd0};
	end else begin
		diff = dividend_copy - divider_copy;
		// if negitave shift a 0 into quotient
		quotient_reg = {quotient_reg[30:0], ~diff[63]};
		divider_copy = {1'b0, divider_copy[63:1]};
		if (!diff[63])
			dividend_copy = diff;
		bit = bit - 1;
	end
end

endmodule

accum_avg/clk_div.v
module clk_div(
	input wire clk,
	input wire rst,
	input [15:0] interval,
	output wire clk_out
);

reg [15:0] counter = 16'd0;
reg clk_out_reg = 1'd0;

assign clk_out = clk_out_reg;

always @(posedge clk) begin
	if (rst) begin
		counter <= 16'd0;
		clk_out_reg <= 1'd0;
	end else begin
		if (counter == interval) begin
			counter <= 16'd0;
			clk_out_reg <= 1'd1;
		end else begin
			counter <= counter + 16'd1;
			clk_out_reg <= 1'd0;
		end
	end	
end

endmodule

accum_avg/accum_and_avg.v
module accum_and_avg (
	input wire clk,
	input wire rst,
	input wire sample_ready,
	input wire [BIT_WIDTH - 1:0] sample,
	output wire [BIT_WIDTH - 1:0] avg
);

parameter BIT_WIDTH = 32;
assign avg = avg_reg;

reg [BIT_WIDTH - 1:0] avg_reg = 0;
reg [BIT_WIDTH - 1:0] accum = 0;
reg [BIT_WIDTH - 1:0] sample_size = 0;

wire div_done_clk;
reg start_div = 1'd0;
wire [BIT_WIDTH - 1:0] quotient;
reg [15:0] clk_counter_reg = 16'd33;


// div_clk MUX
wire div_clk = div_clk_reg;
reg div_clk_enable = 1'd0;
reg div_clk_reg = 1'd0;
always @(*) begin
	if (div_clk_enable) begin
		div_clk_reg <= clk;
	end else begin
		div_clk_reg <= 1'd0;
	end
end

clk_div div_clk_counter(
	.clk(div_clk),
	.rst(rst),
	.interval(clk_counter_reg),
	.clk_out(div_done_clk)
);

div compute_avg(
	.clk(div_clk),
	.start(start_div),
	.dividend(accum),
	.divider(sample_size),
	.quotient(quotient)
);

reg state = 1'd0;
always @(posedge clk) begin
	case (state)
	1'd0:
	begin
		// accumulate sample value
		if (sample_ready) begin
			accum <= accum + sample;
			sample_size <= sample_size + 1;
			// re-calc average with new accum value
			state <= 1'd1;
			start_div <= 1'd1;
			div_clk_enable <= 1'd1;
		end
	end
	1'd1:
	begin
		// average values
		if (div_done_clk) begin
			/*
			* when division is done go back
			* to waiting for more samples
			*/
			state <= 1'd0;
			start_div <= 1'd0;
			avg_reg <= quotient;
			div_clk_enable <= 1'd0;
		end
		
	end
	default:
	begin
		state <= 1'd0;
	end
	endcase
end

endmodule

accum_avg/tb.v
module tb;

reg clk_reg = 1'd0;
wire clk = clk_reg;
wire rst = 0;

reg sample_ready_reg = 1'd1;
wire sample_ready = sample_ready_reg;

reg [31:0] sample = 32'd0;
wire [31:0] avg;

task clk_div;
	begin
		#5
		clk_reg <= ~clk_reg;
		#5
		clk_reg <= ~clk_reg;
	end
endtask

integer i;
initial
begin
	$dumpfile("output.vcd");
	$dumpvars(0, tb);
	sample <= 32'd5;
	#5
	$monitor("avg = %d\n", avg);
	for (i = 0; i < 3000; i++) begin
		clk_div();
		sample <= 32'd7;
	end
	$finish;
end

accum_and_avg aaa(
	.clk(clk),
	.rst(rst),
	.sample_ready(sample_ready),
	.sample(sample),
	.avg(avg)
);

endmodule

accum_avg/output.vcd
$date
	Thu Jul 18 19:30:05 2019
$end
$version
	Icarus Verilog
$end
$timescale
	1s
$end
$scope module tb $end
$var wire 1 ! clk $end
$var wire 1 " rst $end
$var wire 1 # sample_ready $end
$var wire 32 $ avg [31:0] $end
$var reg 1 % clk_reg $end
$var reg 32 & sample [31:0] $end
$var reg 1 ' sample_ready_reg $end
$var integer 32 ( i [31:0] $end
$scope module aaa $end
$var wire 32 ) avg [31:0] $end
$var wire 1 ! clk $end
$var wire 1 * div_clk $end
$var wire 1 " rst $end
$var wire 32 + sample [31:0] $end
$var wire 1 # sample_ready $end
$var wire 32 , quotient [31:0] $end
$var wire 1 - div_done_clk $end
$var reg 32 . accum [31:0] $end
$var reg 32 / avg_reg [31:0] $end
$var reg 16 0 clk_counter_reg [15:0] $end
$var reg 1 1 div_clk_enable $end
$var reg 1 2 div_clk_reg $end
$var reg 32 3 sample_size [31:0] $end
$var reg 1 4 start_div $end
$var reg 1 5 state $end
$scope module compute_avg $end
$var wire 1 * clk $end
$var wire 32 6 dividend [31:0] $end
$var wire 32 7 divider [31:0] $end
$var wire 32 8 quotient [31:0] $end
$var wire 1 4 start $end
$var wire 32 9 remander [31:0] $end
$var wire 1 : ready $end
$var reg 6 ; bit [5:0] $end
$var reg 64 < diff [63:0] $end
$var reg 64 = dividend_copy [63:0] $end
$var reg 64 > divider_copy [63:0] $end
$var reg 32 ? quotient_reg [31:0] $end
$var reg 32 @ result [31:0] $end
$upscope $end
$scope module div_clk_counter $end
$var wire 1 * clk $end
$var wire 1 - clk_out $end
$var wire 16 A interval [15:0] $end
$var wire 1 " rst $end
$var reg 1 B clk_out_reg $end
$var reg 16 C counter [15:0] $end
$upscope $end
$upscope $end
$scope task clk_div $end
$upscope $end
$upscope $end
$enddefinitions $end
#0
$dumpvars
b0 C
0B
b100001 A
bx @
bx ?
bx >
bx =
bx <
b0 ;
1:
bx 9
bx 8
b0 7
b0 6
05
04
b0 3
02
01
b100001 0
b0 /
b0 .
0-
bx ,
b101 +
0*
b0 )
bx (
1'
b101 &
0%
b0 $
1#
0"
0!
$end
#5
b0 (
#10
b1 C
b101 9
b10000000000000000000000000000000 >
b101 =
b0 ?
0:
b100000 ;
1*
12
11
14
15
b1 3
b1 7
b101 .
b101 6
1!
1%
#15
0*
02
b111 &
b111 +
0!
0%
b1 (
#20
b10 C
b11111 ;
b1000000000000000000000000000000 >
b1111111111111111111111111111111110000000000000000000000000000101 <
1*
12
1!
1%
#25
0*
02
0!
0%
b10 (
#30
b11 C
b11110 ;
b100000000000000000000000000000 >
b1111111111111111111111111111111111000000000000000000000000000101 <
1*
12
1!
1%
#35
0*
02
0!
0%
b11 (
#40
b100 C
b11101 ;
b10000000000000000000000000000 >
b1111111111111111111111111111111111100000000000000000000000000101 <
1*
12
1!
1%
#45
0*
02
0!
0%
b100 (
#50
b101 C
b11100 ;
b1000000000000000000000000000 >
b1111111111111111111111111111111111110000000000000000000000000101 <
1*
12
1!
1%
#55
0*
02
0!
0%
b101 (
#60
b110 C
b11011 ;
b100000000000000000000000000 >
b1111111111111111111111111111111111111000000000000000000000000101 <
1*
12
1!
1%
#65
0*
02
0!
0%
b110 (
#70
b111 C
b11010 ;
b10000000000000000000000000 >
b1111111111111111111111111111111111111100000000000000000000000101 <
1*
12
1!
1%
#75
0*
02
0!
0%
b111 (
#80
b1000 C
b11001 ;
b1000000000000000000000000 >
b1111111111111111111111111111111111111110000000000000000000000101 <
1*
12
1!
1%
#85
0*
02
0!
0%
b1000 (
#90
b1001 C
b11000 ;
b100000000000000000000000 >
b1111111111111111111111111111111111111111000000000000000000000101 <
1*
12
1!
1%
#95
0*
02
0!
0%
b1001 (
#100
b1010 C
b10111 ;
b10000000000000000000000 >
b1111111111111111111111111111111111111111100000000000000000000101 <
1*
12
1!
1%
#105
0*
02
0!
0%
b1010 (
#110
b1011 C
b10110 ;
b1000000000000000000000 >
b1111111111111111111111111111111111111111110000000000000000000101 <
1*
12
1!
1%
#115
0*
02
0!
0%
b1011 (
#120
b1100 C
b10101 ;
b100000000000000000000 >
b1111111111111111111111111111111111111111111000000000000000000101 <
1*
12
1!
1%
#125
0*
02
0!
0%
b1100 (
#130
b1101 C
b10100 ;
b10000000000000000000 >
b1111111111111111111111111111111111111111111100000000000000000101 <
1*
12
1!
1%
#135
0*
02
0!
0%
b1101 (
#140
b1110 C
b10011 ;
b1000000000000000000 >
b1111111111111111111111111111111111111111111110000000000000000101 <
1*
12
1!
1%
#145
0*
02
0!
0%
b1110 (
#150
b1111 C
b10010 ;
b100000000000000000 >
b1111111111111111111111111111111111111111111111000000000000000101 <
1*
12
1!
1%
#155
0*
02
0!
0%
b1111 (
#160
b10000 C
b10001 ;
b10000000000000000 >
b1111111111111111111111111111111111111111111111100000000000000101 <
1*
12
1!
1%
#165
0*
02
0!
0%
b10000 (
#170
b10001 C
b10000 ;
b1000000000000000 >
b1111111111111111111111111111111111111111111111110000000000000101 <
1*
12
1!
1%
#175
0*
02
0!
0%
b10001 (
#180
b10010 C
b1111 ;
b100000000000000 >
b1111111111111111111111111111111111111111111111111000000000000101 <
1*
12
1!
1%
#185
0*
02
0!
0%
b10010 (
#190
b10011 C
b1110 ;
b10000000000000 >
b1111111111111111111111111111111111111111111111111100000000000101 <
1*
12
1!
1%
#195
0*
02
0!
0%
b10011 (
#200
b10100 C
b1101 ;
b1000000000000 >
b1111111111111111111111111111111111111111111111111110000000000101 <
1*
12
1!
1%
#205
0*
02
0!
0%
b10100 (
#210
b10101 C
b1100 ;
b100000000000 >
b1111111111111111111111111111111111111111111111111111000000000101 <
1*
12
1!
1%
#215
0*
02
0!
0%
b10101 (
#220
b10110 C
b1011 ;
b10000000000 >
b1111111111111111111111111111111111111111111111111111100000000101 <
1*
12
1!
1%
#225
0*
02
0!
0%
b10110 (
#230
b10111 C
b1010 ;
b1000000000 >
b1111111111111111111111111111111111111111111111111111110000000101 <
1*
12
1!
1%
#235
0*
02
0!
0%
b10111 (
#240
b11000 C
b1001 ;
b100000000 >
b1111111111111111111111111111111111111111111111111111111000000101 <
1*
12
1!
1%
#245
0*
02
0!
0%
b11000 (
#250
b11001 C
b1000 ;
b10000000 >
b1111111111111111111111111111111111111111111111111111111100000101 <
1*
12
1!
1%
#255
0*
02
0!
0%
b11001 (
#260
b11010 C
b111 ;
b1000000 >
b1111111111111111111111111111111111111111111111111111111110000101 <
1*
12
1!
1%
#265
0*
02
0!
0%
b11010 (
#270
b11011 C
b110 ;
b100000 >
b1111111111111111111111111111111111111111111111111111111111000101 <
1*
12
1!
1%
#275
0*
02
0!
0%
b11011 (
#280
b11100 C
b101 ;
b10000 >
b1111111111111111111111111111111111111111111111111111111111100101 <
1*
12
1!
1%
#285
0*
02
0!
0%
b11100 (
#290
b11101 C
b100 ;
b1000 >
b1111111111111111111111111111111111111111111111111111111111110101 <
1*
12
1!
1%
#295
0*
02
0!
0%
b11101 (
#300
b11110 C
b11 ;
b100 >
b1111111111111111111111111111111111111111111111111111111111111101 <
1*
12
1!
1%
#305
0*
02
0!
0%
b11110 (
#310
b11111 C
b1 9
b10 ;
b1 =
b10 >
b1 ?
b1 <
1*
12
1!
1%
#315
0*
02
0!
0%
b11111 (
#320
b100000 C
b1 ;
b1 >
b10 ?
b1111111111111111111111111111111111111111111111111111111111111111 <
1*
12
1!
1%
#325
0*
02
0!
0%
b100000 (
#330
b100001 C
b0 9
1:
b0 ;
b0 =
b0 >
b101 ?
b0 <
1*
12
1!
1%
#335
0*
02
0!
0%
b100001 (
#340
b101 ,
b101 8
b101 @
1-
1B
b0 C
b101 9
b10000000000000000000000000000000 >
b101 =
b0 ?
0:
b100000 ;
1*
12
1!
1%
#345
0*
02
0!
0%
b100010 (
#350
0-
0B
b1 C
b11111 ;
b1000000000000000000000000000000 >
b1111111111111111111111111111111110000000000000000000000000000101 <
01
b101 $
b101 )
b101 /
04
05
0*
02
1!
1%
#355
0!
0%
b100011 (
#360
b10 C
b11110 ;
b100000000000000000000000000000 >
b1111111111111111111111111111111111000000000000000000000000000101 <
1*
12
11
14
15
b10 3
b10 7
b1100 .
b1100 6
1!
1%
#365
0*
02
0!
0%
b100100 (
#370
b11 C
b11101 ;
b10000000000000000000000000000 >
b1111111111111111111111111111111111100000000000000000000000000101 <
1*
12
1!
1%
#375
0*
02
0!
0%
b100101 (
#380
b100 C
b11100 ;
b1000000000000000000000000000 >
b1111111111111111111111111111111111110000000000000000000000000101 <
1*
12
1!
1%
#385
0*
02
0!
0%
b100110 (
#390
b101 C
b11011 ;
b100000000000000000000000000 >
b1111111111111111111111111111111111111000000000000000000000000101 <
1*
12
1!
1%
#395
0*
02
0!
0%
b100111 (
#400
b110 C
b11010 ;
b10000000000000000000000000 >
b1111111111111111111111111111111111111100000000000000000000000101 <
1*
12
1!
1%
#405
0*
02
0!
0%
b101000 (
#410
b111 C
b11001 ;
b1000000000000000000000000 >
b1111111111111111111111111111111111111110000000000000000000000101 <
1*
12
1!
1%
#415
0*
02
0!
0%
b101001 (
#420
b1000 C
b11000 ;
b100000000000000000000000 >
b1111111111111111111111111111111111111111000000000000000000000101 <
1*
12
1!
1%
#425
0*
02
0!
0%
b101010 (
#430
b1001 C
b10111 ;
b10000000000000000000000 >
b1111111111111111111111111111111111111111100000000000000000000101 <
1*
12
1!
1%
#435
0*
02
0!
0%
b101011 (
#440
b1010 C
b10110 ;
b1000000000000000000000 >
b1111111111111111111111111111111111111111110000000000000000000101 <
1*
12
1!
1%
#445
0*
02
0!
0%
b101100 (
#450
b1011 C
b10101 ;
b100000000000000000000 >
b1111111111111111111111111111111111111111111000000000000000000101 <
1*
12
1!
1%
#455
0*
02
0!
0%
b101101 (
#460
b1100 C
b10100 ;
b10000000000000000000 >
b1111111111111111111111111111111111111111111100000000000000000101 <
1*
12
1!
1%
#465
0*
02
0!
0%
b101110 (
#470
b1101 C
b10011 ;
b1000000000000000000 >
b1111111111111111111111111111111111111111111110000000000000000101 <
1*
12
1!
1%
#475
0*
02
0!
0%
b101111 (
#480
b1110 C
b10010 ;
b100000000000000000 >
b1111111111111111111111111111111111111111111111000000000000000101 <
1*
12
1!
1%
#485
0*
02
0!
0%
b110000 (
#490
b1111 C
b10001 ;
b10000000000000000 >
b1111111111111111111111111111111111111111111111100000000000000101 <
1*
12
1!
1%
#495
0*
02
0!
0%
b110001 (
#500
b10000 C
b10000 ;
b1000000000000000 >
b1111111111111111111111111111111111111111111111110000000000000101 <
1*
12
1!
1%
#505
0*
02
0!
0%
b110010 (
#510
b10001 C
b1111 ;
b100000000000000 >
b1111111111111111111111111111111111111111111111111000000000000101 <
1*
12
1!
1%
#515
0*
02
0!
0%
b110011 (
#520
b10010 C
b1110 ;
b10000000000000 >
b1111111111111111111111111111111111111111111111111100000000000101 <
1*
12
1!
1%
#525
0*
02
0!
0%
b110100 (
#530
b10011 C
b1101 ;
b1000000000000 >
b1111111111111111111111111111111111111111111111111110000000000101 <
1*
12
1!
1%
#535
0*
02
0!
0%
b110101 (
#540
b10100 C
b1100 ;
b100000000000 >
b1111111111111111111111111111111111111111111111111111000000000101 <
1*
12
1!
1%
#545
0*
02
0!
0%
b110110 (
#550
b10101 C
b1011 ;
b10000000000 >
b1111111111111111111111111111111111111111111111111111100000000101 <
1*
12
1!
1%
#555
0*
02
0!
0%
b110111 (
#560
b10110 C
b1010 ;
b1000000000 >
b1111111111111111111111111111111111111111111111111111110000000101 <
1*
12
1!
1%
#565
0*
02
0!
0%
b111000 (
#570
b10111 C
b1001 ;
b100000000 >
b1111111111111111111111111111111111111111111111111111111000000101 <
1*
12
1!
1%
#575
0*
02
0!
0%
b111001 (
#580
b11000 C
b1000 ;
b10000000 >
b1111111111111111111111111111111111111111111111111111111100000101 <
1*
12
1!
1%
#585
0*
02
0!
0%
b111010 (
#590
b11001 C
b111 ;
b1000000 >
b1111111111111111111111111111111111111111111111111111111110000101 <
1*
12
1!
1%
#595
0*
02
0!
0%
b111011 (
#600
b11010 C
b110 ;
b100000 >
b1111111111111111111111111111111111111111111111111111111111000101 <
1*
12
1!
1%
#605
0*
02
0!
0%
b111100 (
#610
b11011 C
b101 ;
b10000 >
b1111111111111111111111111111111111111111111111111111111111100101 <
1*
12
1!
1%
#615
0*
02
0!
0%
b111101 (
#620
b11100 C
b100 ;
b1000 >
b1111111111111111111111111111111111111111111111111111111111110101 <
1*
12
1!
1%
#625
0*
02
0!
0%
b111110 (
#630
b11101 C
b11 ;
b100 >
b1111111111111111111111111111111111111111111111111111111111111101 <
1*
12
1!
1%
#635
0*
02
0!
0%
b111111 (
#640
b11110 C
b1 9
b10 ;
b1 =
b10 >
b1 ?
b1 <
1*
12
1!
1%
#645
0*
02
0!
0%
b1000000 (
#650
b11111 C
b1 ;
b1 >
b10 ?
b1111111111111111111111111111111111111111111111111111111111111111 <
1*
12
1!
1%
#655
0*
02
0!
0%
b1000001 (
#660
b100000 C
b0 9
1:
b0 ;
b0 =
b0 >
b101 ?
b0 <
1*
12
1!
1%
#665
0*
02
0!
0%
b1000010 (
#670
b100001 C
b1100 9
b100000000000000000000000000000000 >
b1100 =
b0 ?
0:
b100000 ;
1*
12
1!
1%
#675
0*
02
0!
0%
b1000011 (
#680
1-
1B
b0 C
b11111 ;
b10000000000000000000000000000000 >
b1111111111111111111111111111111100000000000000000000000000001100 <
1*
12
1!
1%
#685
0*
02
0!
0%
b1000100 (
#690
0-
0B
b1 C
b11110 ;
b1000000000000000000000000000000 >
b1111111111111111111111111111111110000000000000000000000000001100 <
01
04
05
0*
02
1!
1%
#695
0!
0%
b1000101 (
#700
b10 C
b11101 ;
b100000000000000000000000000000 >
b1111111111111111111111111111111111000000000000000000000000001100 <
1*
12
11
14
15
b11 3
b11 7
b10011 .
b10011 6
1!
1%
#705
0*
02
0!
0%
b1000110 (
#710
b11 C
b11100 ;
b10000000000000000000000000000 >
b1111111111111111111111111111111111100000000000000000000000001100 <
1*
12
1!
1%
#715
0*
02
0!
0%
b1000111 (
#720
b100 C
b11011 ;
b1000000000000000000000000000 >
b1111111111111111111111111111111111110000000000000000000000001100 <
1*
12
1!
1%
#725
0*
02
0!
0%
b1001000 (
#730
b101 C
b11010 ;
b100000000000000000000000000 >
b1111111111111111111111111111111111111000000000000000000000001100 <
1*
12
1!
1%
#735
0*
02
0!
0%
b1001001 (
#740
b110 C
b11001 ;
b10000000000000000000000000 >
b1111111111111111111111111111111111111100000000000000000000001100 <
1*
12
1!
1%
#745
0*
02
0!
0%
b1001010 (
#750
b111 C
b11000 ;
b1000000000000000000000000 >
b1111111111111111111111111111111111111110000000000000000000001100 <
1*
12
1!
1%
#755
0*
02
0!
0%
b1001011 (
#760
b1000 C
b10111 ;
b100000000000000000000000 >
b1111111111111111111111111111111111111111000000000000000000001100 <
1*
12
1!
1%
#765
0*
02
0!
0%
b1001100 (
#770
b1001 C
b10110 ;
b10000000000000000000000 >
b1111111111111111111111111111111111111111100000000000000000001100 <
1*
12
1!
1%
#775
0*
02
0!
0%
b1001101 (
#780
b1010 C
b10101 ;
b1000000000000000000000 >
b1111111111111111111111111111111111111111110000000000000000001100 <
1*
12
1!
1%
#785
0*
02
0!
0%
b1001110 (
#790
b1011 C
b10100 ;
b100000000000000000000 >
b1111111111111111111111111111111111111111111000000000000000001100 <
1*
12
1!
1%
#795
0*
02
0!
0%
b1001111 (
#800
b1100 C
b10011 ;
b10000000000000000000 >
b1111111111111111111111111111111111111111111100000000000000001100 <
1*
12
1!
1%
#805
0*
02
0!
0%
b1010000 (
#810
b1101 C
b10010 ;
b1000000000000000000 >
b1111111111111111111111111111111111111111111110000000000000001100 <
1*
12
1!
1%
#815
0*
02
0!
0%
b1010001 (
#820
b1110 C
b10001 ;
b100000000000000000 >
b1111111111111111111111111111111111111111111111000000000000001100 <
1*
12
1!
1%
#825
0*
02
0!
0%
b1010010 (
#830
b1111 C
b10000 ;
b10000000000000000 >
b1111111111111111111111111111111111111111111111100000000000001100 <
1*
12
1!
1%
#835
0*
02
0!
0%
b1010011 (
#840
b10000 C
b1111 ;
b1000000000000000 >
b1111111111111111111111111111111111111111111111110000000000001100 <
1*
12
1!
1%
#845
0*
02
0!
0%
b1010100 (
#850
b10001 C
b1110 ;
b100000000000000 >
b1111111111111111111111111111111111111111111111111000000000001100 <
1*
12
1!
1%
#855
0*
02
0!
0%
b1010101 (
#860
b10010 C
b1101 ;
b10000000000000 >
b1111111111111111111111111111111111111111111111111100000000001100 <
1*
12
1!
1%
#865
0*
02
0!
0%
b1010110 (
#870
b10011 C
b1100 ;
b1000000000000 >
b1111111111111111111111111111111111111111111111111110000000001100 <
1*
12
1!
1%
#875
0*
02
0!
0%
b1010111 (
#880
b10100 C
b1011 ;
b100000000000 >
b1111111111111111111111111111111111111111111111111111000000001100 <
1*
12
1!
1%
#885
0*
02
0!
0%
b1011000 (
#890
b10101 C
b1010 ;
b10000000000 >
b1111111111111111111111111111111111111111111111111111100000001100 <
1*
12
1!
1%
#895
0*
02
0!
0%
b1011001 (
#900
b10110 C
b1001 ;
b1000000000 >
b1111111111111111111111111111111111111111111111111111110000001100 <
1*
12
1!
1%
#905
0*
02
0!
0%
b1011010 (
#910
b10111 C
b1000 ;
b100000000 >
b1111111111111111111111111111111111111111111111111111111000001100 <
1*
12
1!
1%
#915
0*
02
0!
0%
b1011011 (
#920
b11000 C
b111 ;
b10000000 >
b1111111111111111111111111111111111111111111111111111111100001100 <
1*
12
1!
1%
#925
0*
02
0!
0%
b1011100 (
#930
b11001 C
b110 ;
b1000000 >
b1111111111111111111111111111111111111111111111111111111110001100 <
1*
12
1!
1%
#935
0*
02
0!
0%
b1011101 (
#940
b11010 C
b101 ;
b100000 >
b1111111111111111111111111111111111111111111111111111111111001100 <
1*
12
1!
1%
#945
0*
02
0!
0%
b1011110 (
#950
b11011 C
b100 ;
b10000 >
b1111111111111111111111111111111111111111111111111111111111101100 <
1*
12
1!
1%
#955
0*
02
0!
0%
b1011111 (
#960
b11100 C
b11 ;
b1000 >
b1111111111111111111111111111111111111111111111111111111111111100 <
1*
12
1!
1%
#965
0*
02
0!
0%
b1100000 (
#970
b11101 C
b100 9
b10 ;
b100 =
b100 >
b1 ?
b100 <
1*
12
1!
1%
#975
0*
02
0!
0%
b1100001 (
#980
b11110 C
b0 9
b1 ;
b0 =
b10 >
b11 ?
b0 <
1*
12
1!
1%
#985
0*
02
0!
0%
b1100010 (
#990
b11111 C
1:
b0 ;
b1 >
b110 ?
b1111111111111111111111111111111111111111111111111111111111111110 <
1*
12
1!
1%
#995
0*
02
0!
0%
b1100011 (
#1000
b110 ,
b110 8
b110 @
b100000 C
b10011 9
b110000000000000000000000000000000 >
b10011 =
b0 ?
0:
b100000 ;
1*
12
1!
1%
#1005
0*
02
0!
0%
b1100100 (
#1010
b100001 C
b11111 ;
b11000000000000000000000000000000 >
b1111111111111111111111111111111010000000000000000000000000010011 <
1*
12
1!
1%
#1015
0*
02
0!
0%
b1100101 (
#1020
1-
1B
b0 C
b11110 ;
b1100000000000000000000000000000 >
b1111111111111111111111111111111101000000000000000000000000010011 <
1*
12
1!
1%
#1025
0*
02
0!
0%
b1100110 (
#1030
0-
0B
b1 C
b11101 ;
b110000000000000000000000000000 >
b1111111111111111111111111111111110100000000000000000000000010011 <
01
b110 $
b110 )
b110 /
04
05
0*
02
1!
1%
#1035
0!
0%
b1100111 (
#1040
b10 C
b11100 ;
b11000000000000000000000000000 >
b1111111111111111111111111111111111010000000000000000000000010011 <
1*
12
11
14
15
b100 3
b100 7
b11010 .
b11010 6
1!
1%
#1045
0*
02
0!
0%
b1101000 (
#1050
b11 C
b11011 ;
b1100000000000000000000000000 >
b1111111111111111111111111111111111101000000000000000000000010011 <
1*
12
1!
1%
#1055
0*
02
0!
0%
b1101001 (
#1060
b100 C
b11010 ;
b110000000000000000000000000 >
b1111111111111111111111111111111111110100000000000000000000010011 <
1*
12
1!
1%
#1065
0*
02
0!
0%
b1101010 (
#1070
b101 C
b11001 ;
b11000000000000000000000000 >
b1111111111111111111111111111111111111010000000000000000000010011 <
1*
12
1!
1%
#1075
0*
02
0!
0%
b1101011 (
#1080
b110 C
b11000 ;
b1100000000000000000000000 >
b1111111111111111111111111111111111111101000000000000000000010011 <
1*
12
1!
1%
#1085
0*
02
0!
0%
b1101100 (
#1090
b111 C
b10111 ;
b110000000000000000000000 >
b1111111111111111111111111111111111111110100000000000000000010011 <
1*
12
1!
1%
#1095
0*
02
0!
0%
b1101101 (
#1100
b1000 C
b10110 ;
b11000000000000000000000 >
b1111111111111111111111111111111111111111010000000000000000010011 <
1*
12
1!
1%
#1105
0*
02
0!
0%
b1101110 (
#1110
b1001 C
b10101 ;
b1100000000000000000000 >
b1111111111111111111111111111111111111111101000000000000000010011 <
1*
12
1!
1%
#1115
0*
02
0!
0%
b1101111 (
#1120
b1010 C
b10100 ;
b110000000000000000000 >
b1111111111111111111111111111111111111111110100000000000000010011 <
1*
12
1!
1%
#1125
0*
02
0!
0%
b1110000 (
#1130
b1011 C
b10011 ;
b11000000000000000000 >
b1111111111111111111111111111111111111111111010000000000000010011 <
1*
12
1!
1%
#1135
0*
02
0!
0%
b1110001 (
#1140
b1100 C
b10010 ;
b1100000000000000000 >
b1111111111111111111111111111111111111111111101000000000000010011 <
1*
12
1!
1%
#1145
0*
02
0!
0%
b1110010 (
#1150
b1101 C
b10001 ;
b110000000000000000 >
b1111111111111111111111111111111111111111111110100000000000010011 <
1*
12
1!
1%
#1155
0*
02
0!
0%
b1110011 (
#1160
b1110 C
b10000 ;
b11000000000000000 >
b1111111111111111111111111111111111111111111111010000000000010011 <
1*
12
1!
1%
#1165
0*
02
0!
0%
b1110100 (
#1170
b1111 C
b1111 ;
b1100000000000000 >
b1111111111111111111111111111111111111111111111101000000000010011 <
1*
12
1!
1%
#1175
0*
02
0!
0%
b1110101 (
#1180
b10000 C
b1110 ;
b110000000000000 >
b1111111111111111111111111111111111111111111111110100000000010011 <
1*
12
1!
1%
#1185
0*
02
0!
0%
b1110110 (
#1190
b10001 C
b1101 ;
b11000000000000 >
b1111111111111111111111111111111111111111111111111010000000010011 <
1*
12
1!
1%
#1195
0*
02
0!
0%
b1110111 (
#1200
b10010 C
b1100 ;
b1100000000000 >
b1111111111111111111111111111111111111111111111111101000000010011 <
1*
12
1!
1%
#1205
0*
02
0!
0%
b1111000 (
#1210
b10011 C
b1011 ;
b110000000000 >
b1111111111111111111111111111111111111111111111111110100000010011 <
1*
12
1!
1%
#1215
0*
02
0!
0%
b1111001 (
#1220
b10100 C
b1010 ;
b11000000000 >
b1111111111111111111111111111111111111111111111111111010000010011 <
1*
12
1!
1%
#1225
0*
02
0!
0%
b1111010 (
#1230
b10101 C
b1001 ;
b1100000000 >
b1111111111111111111111111111111111111111111111111111101000010011 <
1*
12
1!
1%
#1235
0*
02
0!
0%
b1111011 (
#1240
b10110 C
b1000 ;
b110000000 >
b1111111111111111111111111111111111111111111111111111110100010011 <
1*
12
1!
1%
#1245
0*
02
0!
0%
b1111100 (
#1250
b10111 C
b111 ;
b11000000 >
b1111111111111111111111111111111111111111111111111111111010010011 <
1*
12
1!
1%
#1255
0*
02
0!
0%
b1111101 (
#1260
b11000 C
b110 ;
b1100000 >
b1111111111111111111111111111111111111111111111111111111101010011 <
1*
12
1!
1%
#1265
0*
02
0!
0%
b1111110 (
#1270
b11001 C
b101 ;
b110000 >
b1111111111111111111111111111111111111111111111111111111110110011 <
1*
12
1!
1%
#1275
0*
02
0!
0%
b1111111 (
#1280
b11010 C
b100 ;
b11000 >
b1111111111111111111111111111111111111111111111111111111111100011 <
1*
12
1!
1%
#1285
0*
02
0!
0%
b10000000 (
#1290
b11011 C
b11 ;
b1100 >
b1111111111111111111111111111111111111111111111111111111111111011 <
1*
12
1!
1%
#1295
0*
02
0!
0%
b10000001 (
#1300
b11100 C
b111 9
b10 ;
b111 =
b110 >
b1 ?
b111 <
1*
12
1!
1%
#1305
0*
02
0!
0%
b10000010 (
#1310
b11101 C
b1 9
b1 ;
b1 =
b11 >
b11 ?
b1 <
1*
12
1!
1%
#1315
0*
02
0!
0%
b10000011 (
#1320
b11110 C
1:
b0 ;
b1 >
b110 ?
b1111111111111111111111111111111111111111111111111111111111111110 <
1*
12
1!
1%
#1325
0*
02
0!
0%
b10000100 (
#1330
b11111 C
b11010 9
b1000000000000000000000000000000000 >
b11010 =
b0 ?
0:
b100000 ;
1*
12
1!
1%
#1335
0*
02
0!
0%
b10000101 (
#1340
b100000 C
b11111 ;
b100000000000000000000000000000000 >
b1111111111111111111111111111111000000000000000000000000000011010 <
1*
12
1!
1%
#1345
0*
02
0!
0%
b10000110 (
#1350
b100001 C
b11110 ;
b10000000000000000000000000000000 >
b1111111111111111111111111111111100000000000000000000000000011010 <
1*
12
1!
1%
#1355
0*
02
0!
0%
b10000111 (
#1360
1-
1B
b0 C
b11101 ;
b1000000000000000000000000000000 >
b1111111111111111111111111111111110000000000000000000000000011010 <
1*
12
1!
1%
#1365
0*
02
0!
0%
b10001000 (
#1370
0-
0B
b1 C
b11100 ;
b100000000000000000000000000000 >
b1111111111111111111111111111111111000000000000000000000000011010 <
01
04
05
0*
02
1!
1%
#1375
0!
0%
b10001001 (
#1380
b10 C
b11011 ;
b10000000000000000000000000000 >
b1111111111111111111111111111111111100000000000000000000000011010 <
1*
12
11
14
15
b101 3
b101 7
b100001 .
b100001 6
1!
1%
#1385
0*
02
0!
0%
b10001010 (
#1390
b11 C
b11010 ;
b1000000000000000000000000000 >
b1111111111111111111111111111111111110000000000000000000000011010 <
1*
12
1!
1%
#1395
0*
02
0!
0%
b10001011 (
#1400
b100 C
b11001 ;
b100000000000000000000000000 >
b1111111111111111111111111111111111111000000000000000000000011010 <
1*
12
1!
1%
#1405
0*
02
0!
0%
b10001100 (
#1410
b101 C
b11000 ;
b10000000000000000000000000 >
b1111111111111111111111111111111111111100000000000000000000011010 <
1*
12
1!
1%
#1415
0*
02
0!
0%
b10001101 (
